minimax_mcp/__init__.py
minimax_mcp/__main__.py
minimax_mcp/client.py
minimax_mcp/const.py
minimax_mcp/exceptions.py
minimax_mcp/server.py
minimax_mcp/utils.py
mseep_minimax_mcp-0.0.15.dist-info/licenses/LICENSE
mseep_minimax_mcp-0.0.15.dist-info/METADATA
mseep_minimax_mcp-0.0.15.dist-info/WHEEL
mseep_minimax_mcp-0.0.15.dist-info/top_level.txt
mseep_minimax_mcp-0.0.15.dist-info/RECORD
